Metadata-Version: 2.4
Name: fred-metadata
Version: 0.0.37
Summary: Metadata generation, validation, search and visualization.
Author-email: Jasmin Walter <Jasmin.Walter@mpi-bn.mpg.de>
License-Expression: MIT
License-File: LICENSE
Requires-Dist: PyYAML>=5.1
Requires-Dist: pytz
Requires-Dist: python-dateutil
Requires-Dist: tabulate
Requires-Dist: seaborn
Requires-Dist: biopython
Requires-Dist: plotly<=6.2.0
Requires-Dist: jinja2
Requires-Dist: gitpython
Requires-Dist: kaleido<1.0.0
Requires-Dist: dash
Requires-Dist: mkdocs
Dynamic: license-file
